jupyterlab_stata_highlight3/__init__.py
jupyterlab_stata_highlight3/_version.py
jupyterlab_stata_highlight3-0.1.6.data/data/share/jupyter/labextensions/jupyterlab-stata-highlight3/build_log.json
jupyterlab_stata_highlight3-0.1.6.data/data/share/jupyter/labextensions/jupyterlab-stata-highlight3/package.json
jupyterlab_stata_highlight3-0.1.6.data/data/share/jupyter/labextensions/jupyterlab-stata-highlight3/schemas/jupyterlab-stata-highlight3/package.json.orig
jupyterlab_stata_highlight3-0.1.6.data/data/share/jupyter/labextensions/jupyterlab-stata-highlight3/schemas/jupyterlab-stata-highlight3/settings.json
jupyterlab_stata_highlight3-0.1.6.data/data/share/jupyter/labextensions/jupyterlab-stata-highlight3/static/lib_index_js.086e3d08c68af35b7d1a.js
jupyterlab_stata_highlight3-0.1.6.data/data/share/jupyter/labextensions/jupyterlab-stata-highlight3/static/lib_index_js.086e3d08c68af35b7d1a.js.map
jupyterlab_stata_highlight3-0.1.6.data/data/share/jupyter/labextensions/jupyterlab-stata-highlight3/static/remoteEntry.0aedc06479719b460832.js
jupyterlab_stata_highlight3-0.1.6.data/data/share/jupyter/labextensions/jupyterlab-stata-highlight3/static/remoteEntry.0aedc06479719b460832.js.map
jupyterlab_stata_highlight3-0.1.6.data/data/share/jupyter/labextensions/jupyterlab-stata-highlight3/static/style.js
jupyterlab_stata_highlight3-0.1.6.data/data/share/jupyter/labextensions/jupyterlab-stata-highlight3/static/style_index_js.84e2d8d724a13d620a97.js
jupyterlab_stata_highlight3-0.1.6.data/data/share/jupyter/labextensions/jupyterlab-stata-highlight3/static/style_index_js.84e2d8d724a13d620a97.js.map
jupyterlab_stata_highlight3-0.1.6.data/data/share/jupyter/labextensions/jupyterlab-stata-highlight3/install.json
jupyterlab_stata_highlight3-0.1.6.dist-info/METADATA
jupyterlab_stata_highlight3-0.1.6.dist-info/WHEEL
jupyterlab_stata_highlight3-0.1.6.dist-info/licenses/LICENSE
jupyterlab_stata_highlight3-0.1.6.dist-info/RECORD
