Metadata-Version: 2.4
Name: jupyterlab_stata_highlight3
Version: 0.1.6
Summary: Stata syntax highlighting for JupyterLab 4+.
Project-URL: Homepage, https://github.com/lutherbu/jupyterlab_stata_highlight3
Project-URL: Bug Tracker, https://github.com/lutherbu/jupyterlab_stata_highlight3/issues
Project-URL: Repository, https://github.com/lutherbu/jupyterlab_stata_highlight3.git
Author-email: lutherbu <luofan.bu@gmail.com>
License: BSD 3-Clause License
License-File: LICENSE
Keywords: jupyter,jupyterlab,jupyterlab-extension
Classifier: Framework :: Jupyter
Classifier: Framework :: Jupyter :: JupyterLab
Classifier: Framework :: Jupyter :: JupyterLab :: 4
Classifier: Framework :: Jupyter :: JupyterLab :: Extensions
Classifier: Framework :: Jupyter :: JupyterLab :: Extensions :: Prebuilt
Classifier: License :: OSI Approved :: BSD License
Classifier: Programming Language :: Python
Classifier: Programming Language :: Python :: 3
Classifier: Programming Language :: Python :: 3.8
Classifier: Programming Language :: Python :: 3.9
Classifier: Programming Language :: Python :: 3.10
Classifier: Programming Language :: Python :: 3.11
Classifier: Programming Language :: Python :: 3.12
Requires-Python: >=3.8
